MultiRunner.py
README.md
setup.cfg
setup.py
MultiRunner.egg-info/PKG-INFO
MultiRunner.egg-info/SOURCES.txt
MultiRunner.egg-info/dependency_links.txt
MultiRunner.egg-info/top_level.txt