Metadata-Version: 2.1
Name: MultiRunner
Version: 6.0
Summary: This is a python package for multi-process running.
Home-page: https://github.com/Statham-stone/MultiRunner
Author: Statham
Author-email: statham.stone@gmail.com
License: UNKNOWN
Platform: UNKNOWN
